{
  "settings": {
    "autoplay": {
      "enabled": true,
      "delay": 4000
    },
    "navigation": {
      "enabled": true,
      "arrows": true,
      "pagination": true
    },
    "loop": true,
    "speed": 600,
    "spaceBetween": 0,
    "slidesPerView": 1
  },
  "breakpoints": {
    "mobile": {
      "maxWidth": 768,
      "settings": {
        "autoplay": { "delay": 3000 },
        "speed": 400
      }
    },
    "tablet": {
      "maxWidth": 1024,
      "settings": {
        "autoplay": { "delay": 3500 }
      }
    }
  },
  "slides": [
    {
      "title": "Welcome to Blazor Boost",
      "subtitle": "Build modern web apps with C# and WebAssembly",
      "buttonText": "Get Started",
      "buttonLink": "#",
      "image": "/images/Slide_1.jpg",
      "overlay": {
        "gradient": "linear-gradient(45deg, rgba(0,0,0,0.6), rgba(0,0,0,0.2))"
      },
      "animations": {
        "title": {
          "preset": "slideUp",
          "delay": 0.3,
          "duration": 0.8,
          "easing": "power2.out"
        },
        "subtitle": {
          "preset": "slideUp", 
          "delay": 0.5,
          "duration": 0.8,
          "easing": "power2.out"
        },
        "cta": {
          "preset": "scaleIn",
          "delay": 0.7,
          "duration": 0.6,
          "easing": "back.out(1.7)"
        }
      },
      "duration": 5000
    },
    {
      "title": "Supercharge Your Productivity",
      "subtitle": "Rapid development with full control over UI",
      "buttonText": "Learn More",
      "buttonLink": "#",
      "image": "/images/Slide_2.jpg",
      "overlay": {
        "gradient": "linear-gradient(135deg, rgba(0,50,100,0.4), rgba(0,0,0,0.6))"
      },
      "animations": {
        "title": {
          "preset": "fadeIn",
          "delay": 0.2,
          "duration": 1.0,
          "easing": "power1.out"
        },
        "subtitle": {
          "preset": "slideInLeft",
          "delay": 0.6,
          "duration": 0.8,
          "easing": "power2.out"
        },
        "cta": {
          "preset": "bounceIn",
          "delay": 1.0,
          "duration": 0.8,
          "easing": "back.out(1.7)"
        }
      },
      "duration": 4500
    },
    {
      "title": "Tailwind + Blazor = ❤️",
      "subtitle": "Style your components with ease",
      "buttonText": "Explore Now",
      "buttonLink": "#",
      "image": "/images/Slide_3.jpg",
      "overlay": {
        "gradient": "linear-gradient(to right, rgba(100,0,100,0.3), rgba(0,0,0,0.5))"
      },
      "animations": {
        "title": {
          "preset": "typewriter",
          "delay": 0.3,
          "duration": 2.0,
          "easing": "none"
        },
        "subtitle": {
          "preset": "slideInSplit",
          "delay": 2.5,
          "duration": 1.2,
          "easing": "power2.out"
        },
        "cta": {
          "preset": "zoomBlur",
          "delay": 4.0,
          "duration": 1.0,
          "easing": "power2.out"
        }
      },
      "duration": 6000
    },
    {
      "title": "Experience Motion",  
      "subtitle": "Dynamic video backgrounds bring your content to life",
      "buttonText": "Watch Demo",
      "buttonLink": "#",
      "video": "https://commondatastorage.googleapis.com/gtv-videos-bucket/sample/BigBuckBunny.mp4",
      "poster": "",
      "videoSettings": {
        "autoplay": true,
        "muted": true,
        "loop": true,
        "controls": false,
        "playbackRate": 1
      },
      "overlay": {
        "gradient": "linear-gradient(45deg, rgba(0,0,0,0.7), rgba(0,0,0,0.3))"
      },
      "animations": {
        "title": {
          "preset": "fadeIn",
          "delay": 0.5,
          "duration": 1.0,
          "easing": "power2.out"
        },
        "subtitle": {
          "preset": "slideUp",
          "delay": 0.8,
          "duration": 0.8,
          "easing": "power2.out"
        },
        "cta": {
          "preset": "zoomIn",
          "delay": 1.2,
          "duration": 0.6,
          "easing": "back.out(1.7)"
        }
      },
      "duration": 5000
    },
    {
      "title": "Smooth Performance",
      "subtitle": "Optimized video playback across all devices",
      "buttonText": "Learn More",
      "buttonLink": "#",
      "video": "https://www.sliderrevolution.com/wp-content/uploads/revslider/2024Type-Slider-Vert/choco2.mp4",
      "poster": "/images/Slide_2.jpg",
      "videoSettings": {
        "autoplay": true,
        "muted": true,
        "loop": true,
        "controls": false,
        "playbackRate": 0.8
      },
      "overlay": {
        "gradient": "linear-gradient(135deg, rgba(0,50,100,0.6), rgba(0,0,0,0.4))"
      },
      "animations": {
        "title": {
          "preset": "slideInLeft",
          "delay": 0.3,
          "duration": 0.9,
          "easing": "power2.out"
        },
        "subtitle": {
          "preset": "slideIn",
          "delay": 0.6,
          "duration": 0.9,
          "easing": "power2.out"
        },
        "cta": {
          "preset": "bounceIn",
          "delay": 1.0,
          "duration": 0.8,
          "easing": "bounce.out"
        }
      },
      "duration": 4500
    },
    {
      "title": "Multi-Layer Content",
      "subtitle": "Simple layered elements test",
      "image": "/images/Slide_1.jpg",
      "overlay": {
        "gradient": "linear-gradient(135deg, rgba(20,20,80,0.7), rgba(0,0,0,0.3))"
      },
      "layers": [
        {
          "type": "text",
          "content": "Phase 3.2",
          "position": "top-right",
          "style": {
            "fontSize": "24px",
            "fontWeight": "bold",
            "color": "#FFD700",
            "padding": "20px"
          },
          "animation": {
            "preset": "slideInRight",
            "delay": 0.3,
            "duration": 0.8
          }
        },
        {
          "type": "text",
          "content": "🚀",
          "position": "bottom-left",
          "style": {
            "fontSize": "48px",
            "margin": "30px"
          },
          "animation": {
            "preset": "bounceIn",
            "delay": 0.6,
            "duration": 0.8
          }
        }
      ],
      "animations": {
        "title": {
          "preset": "slideUp",
          "delay": 0.3,
          "duration": 0.8,
          "easing": "power2.out"
        },
        "subtitle": {
          "preset": "slideUp",
          "delay": 0.4,
          "duration": 0.8,
          "easing": "power2.out"
        }
      },
      "duration": 5000
    },
    {
      "image": "/images/Slide_3.jpg",
      "overlay": {
        "gradient": "linear-gradient(45deg, rgba(100,0,150,0.8), rgba(0,0,0,0.4))"
      },
      "layers": [
        {
          "type": "text",
          "content": "Advanced",
          "position": "top-center",
          "style": {
            "fontSize": "32px",
            "fontWeight": "900",
            "color": "#FF6B6B",
            "textShadow": "2px 2px 4px rgba(0,0,0,0.8)",
            "marginTop": "40px"
          },
          "animation": {
            "preset": "fadeIn",
            "delay": 0.2,
            "duration": 1.0,
            "easing": "power2.out"
          }
        },
        {
          "type": "text",
          "content": "Multi-Layer System",
          "position": "center",
          "style": {
            "fontSize": "48px",
            "fontWeight": "bold",
            "color": "white",
            "textAlign": "center",
            "textShadow": "3px 3px 6px rgba(0,0,0,0.8)",
            "lineHeight": "1.2"
          },
          "animation": {
            "preset": "slideUp",
            "delay": 0.5,
            "duration": 0.9,
            "easing": "power2.out"
          }
        },
        {
          "type": "image",
          "src": "/images/Slide_2.jpg",
          "alt": "Feature showcase",
          "position": "middle-left",
          "style": {
            "width": "300px",
            "height": "200px",
            "borderRadius": "15px",
            "boxShadow": "0 10px 30px rgba(0,0,0,0.5)",
            "transform": "translateX(-50px)"
          },
          "animation": {
            "preset": "slideInLeft",
            "delay": 0.8,
            "duration": 0.8,
            "easing": "power2.out"
          }
        },
        {
          "type": "custom",
          "html": "<div style='background: linear-gradient(45deg, #FF6B6B, #4ECDC4); padding: 20px; border-radius: 10px; backdrop-filter: blur(10px);'><h3 style='margin: 0; color: white; font-size: 18px;'>Enhanced Layers</h3><p style='margin: 8px 0 0 0; color: rgba(255,255,255,0.9); font-size: 14px;'>Independent animations</p></div>",
          "position": "bottom-right",
          "style": {
            "margin": "30px"
          },
          "animation": {
            "preset": "zoomIn",
            "delay": 1.1,
            "duration": 0.7,
            "easing": "back.out(1.7)"
          }
        },
        {
          "type": "text",
          "content": "✨",
          "position": "top-left",
          "style": {
            "fontSize": "36px",
            "margin": "20px",
            "opacity": "0.8"
          },
          "animation": {
            "preset": "rotateIn",
            "delay": 1.4,
            "duration": 0.8,
            "easing": "power2.out"
          }
        }
      ],
      "duration": 7000
    },
    {
      "title": "Phase 3.2 Complete",
      "subtitle": "Advanced Multi-Layer Content System",
      "image": "/images/Slide_1.jpg",
      "overlay": {
        "gradient": "linear-gradient(135deg, rgba(0,20,50,0.9), rgba(0,0,0,0.5))"
      },
      "layers": [
        {
          "type": "text",
          "content": "🎯",
          "position": "custom",
          "x": 100,
          "y": 100,
          "style": {
            "fontSize": "60px",
            "filter": "drop-shadow(0 0 20px rgba(255,215,0,0.8))"
          },
          "animation": {
            "preset": "rotateIn",
            "delay": 0.3,
            "duration": 1.2,
            "easing": "back.out(1.7)"
          }
        },
        {
          "type": "custom",
          "html": "<div style='background: rgba(255,255,255,0.1); backdrop-filter: blur(15px); border-radius: 20px; padding: 25px; border: 2px solid rgba(255,255,255,0.2); box-shadow: 0 10px 40px rgba(0,0,0,0.3);'><h4 style='margin: 0 0 15px 0; color: #4ECDC4; font-size: 20px; font-weight: 700;'>🚀 Features Achieved</h4><ul style='margin: 0; padding: 0; list-style: none; color: rgba(255,255,255,0.9); font-size: 16px; line-height: 1.6;'><li>✅ Multiple Layer Types</li><li>✅ Custom Positioning</li><li>✅ Advanced Animations</li><li>✅ Sequential Timing</li></ul></div>",
          "position": "custom",
          "x": 50,
          "y": 300,
          "style": {
            "width": "350px"
          },
          "animation": {
            "preset": "slideInLeft",
            "delay": 0.8,
            "duration": 1.0,
            "easing": "power2.out"
          }
        },
        {
          "type": "image",
          "src": "/images/Slide_3.jpg",
          "alt": "Success showcase",
          "position": "custom",
          "x": 600,
          "y": 150,
          "style": {
            "width": "200px",
            "height": "150px",
            "borderRadius": "20px",
            "boxShadow": "0 15px 50px rgba(0,0,0,0.4)",
            "border": "3px solid rgba(255,255,255,0.3)"
          },
          "animation": {
            "preset": "zoomIn",
            "delay": 1.2,
            "duration": 0.8,
            "easing": "back.out(1.4)"
          }
        },
        {
          "type": "text",
          "content": "Complete!",
          "position": "custom",
          "x": 550,
          "y": 350,
          "style": {
            "fontSize": "36px",
            "fontWeight": "900",
            "color": "#FF6B6B",
            "textShadow": "0 0 20px rgba(255,107,107,0.6)",
            "transform": "rotate(-15deg)"
          },
          "animation": {
            "preset": "bounceIn",
            "delay": 1.6,
            "duration": 1.0,
            "easing": "bounce.out"
          }
        }
      ],
      "animations": {
        "title": {
          "preset": "slideUp",
          "delay": 0.2,
          "duration": 0.8,
          "easing": "power2.out"
        },
        "subtitle": {
          "preset": "slideUp",
          "delay": 0.4,
          "duration": 0.8,
          "easing": "power2.out"
        }
      },
      "duration": 8000
    },
    {
      "title": "Interactive Layers",
      "subtitle": "Click and hover to interact",
      "image": "/images/Slide_2.jpg",
      "overlay": {
        "gradient": "linear-gradient(135deg, rgba(0,100,150,0.8), rgba(0,0,0,0.5))"
      },
      "layers": [
        {
          "type": "button",
          "content": "Click Me!",
          "position": "center",
          "style": {
            "marginTop": "100px"
          },
          "buttonColor": "#FF6B6B",
          "interactive": true,
          "animation": {
            "preset": "bounceIn",
            "delay": 0.5,
            "duration": 0.8,
            "easing": "bounce.out"
          }
        },
        {
          "type": "text",
          "content": "Hover over me! 🎯",
          "position": "top-right",
          "style": {
            "fontSize": "24px",
            "color": "#4ECDC4",
            "padding": "20px",
            "transition": "all 0.3s ease"
          },
          "interactive": true,
          "animation": {
            "preset": "slideInRight",
            "delay": 0.8,
            "duration": 0.6,
            "easing": "power2.out"
          }
        }
      ],
      "animations": {
        "title": {
          "preset": "slideUp",
          "delay": 0.2,
          "duration": 0.8,
          "easing": "power2.out"
        },
        "subtitle": {
          "preset": "slideUp",
          "delay": 0.3,
          "duration": 0.8,
          "easing": "power2.out"
        }
      },
      "duration": 6000
    }
  ]
}
